.gitignore
.isort.cfg
.pre-commit-config.yaml
LICENSE
Makefile
README.rst
phpserialize3.py
pyproject.toml
setup.cfg
setup.py
tests.py
phpserialize3.egg-info/PKG-INFO
phpserialize3.egg-info/SOURCES.txt
phpserialize3.egg-info/dependency_links.txt
phpserialize3.egg-info/not-zip-safe
phpserialize3.egg-info/top_level.txt