Metadata-Version: 1.1
Name: phpserialize3
Version: 0.1.3
Summary: fork from http://github.com/mitsuhiko/phpserializeh
Home-page: http://github.com/codeif/phpserialize3
Author: Armin Ronacher
Author-email: armin.ronacher@active-4.com
License: UNKNOWN
Platform: UNKNOWN
Classifier: License :: OSI Approved :: BSD License
Classifier: Programming Language :: PHP
Classifier: Programming Language :: Python
Classifier: Programming Language :: Python :: 3
